thanos/SyntheticDataset.py
thanos/__init__.py
thanos/gen.py
thanos/operator.py
thanos/rebasis.py
thanos/signal_library.py
thanos/util.py
thanos_gen-0.1.0.dist-info/LICENSE
thanos_gen-0.1.0.dist-info/METADATA
thanos_gen-0.1.0.dist-info/WHEEL
thanos_gen-0.1.0.dist-info/RECORD
